Webtrench/AudioScrapper.py
Webtrench/ImageScrapper.py
Webtrench/MetaDataScrapper.py
Webtrench/TextScrapper.py
Webtrench/VideoScrapper.py
Webtrench/__init__.py
Webtrench/helper.py
Webtrench-0.1.2.dist-info/LICENSE
Webtrench-0.1.2.dist-info/METADATA
Webtrench-0.1.2.dist-info/WHEEL
Webtrench-0.1.2.dist-info/top_level.txt
Webtrench-0.1.2.dist-info/RECORD
